Workbook
Name Slicer_Department: #N/A
Name Slicer_Quarter: #N/A
Name Slicer_Status: #N/A

Sheet Raw_Actuals
A1: Transaction_ID | B1: Month_Num | C1: Month_Name | D1: Quarter | E1: Department | F1: Expense_Category | G1: Vendor | H1: Amount (INR) | I1: Approved_By | J1: Notes | K1: Notes | N1: Notes
A2: TXN-1083 | B2: 2 | C2: Feb | D2: Q1 | E2: Marketing | F2: Payroll | G2: ADP Payroll Services | H2: 92400 | I2: Rahul Mehta | K2: =IF(J2=$N$2,0,IF(J2=$N$3,1,IF(J2=$N$4,2))) -> 0
A3: TXN-1186 | B3: 3 | C3: Mar | D3: Q1 | E3: Operations | F3: Payroll | G3: ADP Payroll Services | H3: 14700 | I3: Sunita Rao | K3: =IF(J3=$N$2,0,IF(J3=$N$3,1,IF(J3=$N$4,2))) -> 0 | N3: Budget overrun - approved by CFO
A4: TXN-1323 | B4: 5 | C4: May | D4: Q2 | E4: IT | F4: Hardware | G4: HP Enterprise | H4: 28400 | I4: Arjun Nair | K4: =IF(J4=$N$2,0,IF(J4=$N$3,1,IF(J4=$N$4,2))) -> 0 | N4: Underspend - deferred to next period
A5: TXN-1765 | B5: 11 | C5: Nov | D5: Q4 | E5: Operations | F5: Maintenance | G5: Facility Services Co. | H5: 8300 | I5: Sunita Rao | K5: =IF(J5=$N$2,0,IF(J5=$N$3,1,IF(J5=$N$4,2))) -> 0
A6: TXN-1856 | B6: 12 | C6: Dec | D6: Q4 | E6: Finance | F6: Software Licenses | G6: Adobe Creative | H6: 3800 | I6: Vikram Joshi | K6: =IF(J6=$N$2,0,IF(J6=$N$3,1,IF(J6=$N$4,2))) -> 0
A7: TXN-1615 | B7: 9 | C7: Oct | D7: Q3 | E7: Operations | F7: Payroll | G7: Paychex | H7: 203200 | I7: Sunita Rao | K7: =IF(J7=$N$2,0,IF(J7=$N$3,1,IF(J7=$N$4,2))) -> 0
A8: TXN-1182 | B8: 3 | C8: Mar | D8: Q1 | E8: IT | F8: Cloud Services | G8: Azure Enterprise | H8: 10900 | I8: Arjun Nair | K8: =IF(J8=$N$2,0,IF(J8=$N$3,1,IF(J8=$N$4,2))) -> 0
A9: TXN-1245 | B9: 4 | C9: Apr | D9: Q2 | E9: IT | F9: Payroll | G9: Gusto HR | H9: 70200 | I9: Arjun Nair | K9: =IF(J9=$N$2,0,IF(J9=$N$3,1,IF(J9=$N$4,2))) -> 0
A10: TXN-1312 | B10: 5 | C10: May | D10: Q2 | E10: Marketing | F10: Events | G10: Webinar Platform | H10: 22800 | I10: Rahul Mehta | K10: =IF(J10=$N$2,0,IF(J10=$N$3,1,IF(J10=$N$4,2))) -> 0
A11: TXN-1260 | B11: 4 | C11: Apr | D11: Q2 | E11: Operations | F11: Logistics | G11: Delhivery | H11: 58900 | I11: Sunita Rao | K11: =IF(J11=$N$2,0,IF(J11=$N$3,1,IF(J11=$N$4,2))) -> 0
A12: TXN-1432 | B12: 7 | C12: Jul | D12: Q3 | E12: HR | F12: Payroll | G12: Gusto HR | H12: 270900 | I12: Priya Sharma | K12: =IF(J12=$N$2,0,IF(J12=$N$3,1,IF(J12=$N$4,2))) -> 0
A13: TXN-1505 | B13: 8 | C13: Aug | D13: Q3 | E13: HR | F13: Payroll | G13: Gusto HR | H13: 204200 | I13: Priya Sharma | K13: =IF(J13=$N$2,0,IF(J13=$N$3,1,IF(J13=$N$4,2))) -> 0
A14: TXN-1456 | B14: 7 | C14: Jul | D14: Q3 | E14: IT | F14: Payroll | G14: Gusto HR | H14: 385800 | I14: Arjun Nair | K14: =IF(J14=$N$2,0,IF(J14=$N$3,1,IF(J14=$N$4,2))) -> 0
A15: TXN-1675 | B15: 10 | C15: Oct | D15: Q4 | E15: Marketing | F15: Travel | G15: Cleartrip Biz | H15: 3100 | I15: Rahul Mehta | K15: =IF(J15=$N$2,0,IF(J15=$N$3,1,IF(J15=$N$4,2))) -> 0
A16: TXN-1034 | B16: 1 | C16: Jan | D16: Q1 | E16: IT | F16: Cloud Services | G16: AWS India | H16: 36700 | I16: Arjun Nair | K16: =IF(J16=$N$2,0,IF(J16=$N$3,1,IF(J16=$N$4,2))) -> 0
... A33: TXN-1409 | B33: 6 | C33: Jun | D33: Q2 | E33: Finance | F33: Audit Fees | G33: Deloitte India | H33: 9100 | I33: Vikram Joshi | K33: =IF(J33=$N$2,0,IF(J33=$N$3,1,IF(J33=$N$4,2))) -> 0
A34: TXN-1368 | B34: 6 | C34: Jun | D34: Q2 | E34: HR | F34: Recruitment | G34: Naukri Corporate | H34: 33400 | I34: Priya Sharma | J34: Budget overrun - approved by CFO | K34: =IF(J34=$N$2,0,IF(J34=$N$3,1,IF(J34=$N$4,2))) -> 1
A35: TXN-1744 | B35: 11 | C35: Nov | D35: Q4 | E35: IT | F35: Payroll | G35: Paychex | H35: 7100 | I35: Arjun Nair | K35: =IF(J35=$N$2,0,IF(J35=$N$3,1,IF(J35=$N$4,2))) -> 0
A36: TXN-1777 | B36: 11 | C36: Nov | D36: Q4 | E36: Finance | F36: Software Licenses | G36: Atlassian Suite | H36: 24300 | I36: Vikram Joshi | K36: =IF(J36=$N$2,0,IF(J36=$N$3,1,IF(J36=$N$4,2))) -> 0
A37: TXN-1696 | B37: 10 | C37: Oct | D37: Q4 | E37: Operations | F37: Maintenance | G37: TechServ India | H37: 27700 | I37: Sunita Rao | K37: =IF(J37=$N$2,0,IF(J37=$N$3,1,IF(J37=$N$4,2))) -> 0
A38: TXN-1596 | B38: 9 | C38: Oct | D38: Q3 | E38: Marketing | F38: Events | G38: Eventbrite Pro | H38: 7300 | I38: Rahul Mehta | K38: =IF(J38=$N$2,0,IF(J38=$N$3,1,IF(J38=$N$4,2))) -> 0
A39: TXN-1762 | B39: 11 | C39: Nov | D39: Q4 | E39: Operations | F39: Logistics | G39: Delhivery | H39: 21300 | I39: Sunita Rao | K39: =IF(J39=$N$2,0,IF(J39=$N$3,1,IF(J39=$N$4,2))) -> 0
A40: TXN-1201 | B40: 3 | C40: Mar | D40: Q1 | E40: Finance | F40: Payroll | G40: Gusto HR | H40: 110800 | I40: Vikram Joshi | K40: =IF(J40=$N$2,0,IF(J40=$N$3,1,IF(J40=$N$4,2))) -> 0
A41: TXN-1770 | B41: 11 | C41: Nov | D41: Q4 | E41: Finance | F41: Payroll | G41: Paychex | H41: 141200 | I41: Vikram Joshi | K41: =IF(J41=$N$2,0,IF(J41=$N$3,1,IF(J41=$N$4,2))) -> 0
A42: TXN-1356 | B42: 5 | C42: May | D42: Q2 | E42: Sales | F42: Travel | G42: SOTC Travel | H42: 2000 | I42: Deepa Patel | K42: =IF(J42=$N$2,0,IF(J42=$N$3,1,IF(J42=$N$4,2))) -> 0
A43: TXN-1013 | B43: 1 | C43: Jan | D43: Q1 | E43: Marketing | F43: Ad Spend | G43: Google Ads | H43: 117500 | I43: Rahul Mehta | K43: =IF(J43=$N$2,0,IF(J43=$N$3,1,IF(J43=$N$4,2))) -> 0
A44: TXN-1527 | B44: 8 | C44: Aug | D44: Q3 | E44: Marketing | F44: Events | G44: Eventbrite Pro | H44: 13100 | I44: Rahul Mehta | K44: =IF(J44=$N$2,0,IF(J44=$N$3,1,IF(J44=$N$4,2))) -> 0
A45: TXN-1620 | B45: 9 | C45: Oct | D45: Q3 | E45: Operations | F45: Logistics | G45: Blue Dart | H45: 800 | I45: Sunita Rao | K45: =IF(J45=$N$2,0,IF(J45=$N$3,1,IF(J45=$N$4,2))) -> 0
A46: TXN-1183 | B46: 3 | C46: Mar | D46: Q1 | E46: IT | F46: Cloud Services | G46: Google Cloud | H46: 3500 | I46: Arjun Nair | K46: =IF(J46=$N$2,0,IF(J46=$N$3,1,IF(J46=$N$4,2))) -> 0
... A54: TXN-1337 | B54: 5 | C54: May | D54: Q2 | E54: Operations | F54: Travel | G54: Cleartrip Biz | H54: 4900 | I54: Sunita Rao | K54: =IF(J54=$N$2,0,IF(J54=$N$3,1,IF(J54=$N$4,2))) -> 0
A55: TXN-1370 | B55: 6 | C55: Jun | D55: Q2 | E55: HR | F55: Recruitment | G55: Naukri Corporate | H55: 16700 | I55: Priya Sharma | J55: Budget overrun - approved by CFO | K55: =IF(J55=$N$2,0,IF(J55=$N$3,1,IF(J55=$N$4,2))) -> 1
A56: TXN-1664 | B56: 10 | C56: Oct | D56: Q4 | E56: Marketing | F56: Payroll | G56: Paychex | H56: 15400 | I56: Rahul Mehta | K56: =IF(J56=$N$2,0,IF(J56=$N$3,1,IF(J56=$N$4,2))) -> 0
A57: TXN-1068 | B57: 1 | C57: Jan | D57: Q1 | E57: Sales | F57: Entertainment | G57: Client Dining | H57: 2400 | I57: Deepa Patel | K57: =IF(J57=$N$2,0,IF(J57=$N$3,1,IF(J57=$N$4,2))) -> 0
A58: TXN-1379 | B58: 6 | C58: Jun | D58: Q2 | E58: Marketing | F58: Ad Spend | G58: LinkedIn Ads | H58: 24000 | I58: Rahul Mehta | K58: =IF(J58=$N$2,0,IF(J58=$N$3,1,IF(J58=$N$4,2))) -> 0
A59: TXN-1613 | B59: 9 | C59: Oct | D59: Q3 | E59: IT | F59: Cloud Services | G59: AWS India | H59: 18800 | I59: Arjun Nair | K59: =IF(J59=$N$2,0,IF(J59=$N$3,1,IF(J59=$N$4,2))) -> 0
A60: TXN-1067 | B60: 1 | C60: Jan | D60: Q1 | E60: Sales | F60: Travel | G60: MakeMyTrip Corporate | H60: 4000 | I60: Deepa Patel | K60: =IF(J60=$N$2,0,IF(J60=$N$3,1,IF(J60=$N$4,2))) -> 0
A61: TXN-1673 | B61: 10 | C61: Oct | D61: Q4 | E61: Marketing | F61: Events | G61: Town Hall Venue | H61: 55000 | I61: Rahul Mehta | K61: =IF(J61=$N$2,0,IF(J61=$N$3,1,IF(J61=$N$4,2))) -> 0
A62: TXN-1328 | B62: 5 | C62: May | D62: Q2 | E62: Operations | F62: Payroll | G62: Paychex | H62: 44600 | I62: Sunita Rao | K62: =IF(J62=$N$2,0,IF(J62=$N$3,1,IF(J62=$N$4,2))) -> 0
A63: TXN-1597 | B63: 9 | C63: Oct | D63: Q3 | E63: Marketing | F63: Events | G63: Town Hall Venue | H63: 5200 | I63: Rahul Mehta | K63: =IF(J63=$N$2,0,IF(J63=$N$3,1,IF(J63=$N$4,2))) -> 0
A64: TXN-1816 | B64: 12 | C64: Dec | D64: Q4 | E64: Marketing | F64: Events | G64: Webinar Platform | H64: 22600 | I64: Rahul Mehta | K64: =IF(J64=$N$2,0,IF(J64=$N$3,1,IF(J64=$N$4,2))) -> 0
A65: TXN-1732 | B65: 11 | C65: Nov | D65: Q4 | E65: Marketing | F65: Payroll | G65: Gusto HR | H65: 16000 | I65: Rahul Mehta | K65: =IF(J65=$N$2,0,IF(J65=$N$3,1,IF(J65=$N$4,2))) -> 0
A66: TXN-1704 | B66: 10 | C66: Oct | D66: Q4 | E66: Finance | F66: Audit Fees | G66: PwC Advisory | H66: 7000 | I66: Vikram Joshi | K66: =IF(J66=$N$2,0,IF(J66=$N$3,1,IF(J66=$N$4,2))) -> 0
A67: TXN-1270 | B67: 4 | C67: Apr | D67: Q2 | E67: Finance | F67: Payroll | G67: Paychex | H67: 46100 | I67: Vikram Joshi | K67: =IF(J67=$N$2,0,IF(J67=$N$3,1,IF(J67=$N$4,2))) -> 0
... A78: TXN-1845 | B78: 12 | C78: Dec | D78: Q4 | E78: Operations | F78: Travel | G78: Cleartrip Biz | H78: 1100 | I78: Sunita Rao | K78: =IF(J78=$N$2,0,IF(J78=$N$3,1,IF(J78=$N$4,2))) -> 0
A79: TXN-1752 | B79: 11 | C79: Nov | D79: Q4 | E79: IT | F79: Hardware | G79: Lenovo B2B | H79: 96000 | I79: Arjun Nair | J79: Budget overrun - approved by CFO | K79: =IF(J79=$N$2,0,IF(J79=$N$3,1,IF(J79=$N$4,2))) -> 1
A80: TXN-1235 | B80: 4 | C80: Apr | D80: Q2 | E80: HR | F80: Travel | G80: SOTC Travel | H80: 5200 | I80: Priya Sharma | K80: =IF(J80=$N$2,0,IF(J80=$N$3,1,IF(J80=$N$4,2))) -> 0
A81: TXN-1720 | B81: 10 | C81: Oct | D81: Q4 | E81: Sales | F81: Entertainment | G81: Event Hospitality | H81: 3100 | I81: Deepa Patel | K81: =IF(J81=$N$2,0,IF(J81=$N$3,1,IF(J81=$N$4,2))) -> 0
A82: TXN-1747 | B82: 11 | C82: Nov | D82: Q4 | E82: IT | F82: Software Licenses | G82: Microsoft 365 | H82: 41200 | I82: Arjun Nair | K82: =IF(J82=$N$2,0,IF(J82=$N$3,1,IF(J82=$N$4,2))) -> 0
A83: TXN-1463 | B83: 7 | C83: Jul | D83: Q3 | E83: IT | F83: Cloud Services | G83: Azure Enterprise | H83: 10500 | I83: Arjun Nair | K83: =IF(J83=$N$2,0,IF(J83=$N$3,1,IF(J83=$N$4,2))) -> 0
A84: TXN-1133 | B84: 2 | C84: Feb | D84: Q1 | E84: Sales | F84: Payroll | G84: ADP Payroll Services | H84: 34500 | I84: Deepa Patel | K84: =IF(J84=$N$2,0,IF(J84=$N$3,1,IF(J84=$N$4,2))) -> 0
A85: TXN-1311 | B85: 5 | C85: May | D85: Q2 | E85: Marketing | F85: Ad Spend | G85: Google Ads | H85: 80700 | I85: Rahul Mehta | J85: Budget overrun - approved by CFO | K85: =IF(J85=$N$2,0,IF(J85=$N$3,1,IF(J85=$N$4,2))) -> 1
A86: TXN-1349 | B86: 5 | C86: May | D86: Q2 | E86: Sales | F86: Payroll | G86: Gusto HR | H86: 42500 | I86: Deepa Patel | K86: =IF(J86=$N$2,0,IF(J86=$N$3,1,IF(J86=$N$4,2))) -> 0
A87: TXN-1313 | B87: 5 | C87: May | D87: Q2 | E87: Marketing | F87: Events | G87: Town Hall Venue | H87: 36200 | I87: Rahul Mehta | K87: =IF(J87=$N$2,0,IF(J87=$N$3,1,IF(J87=$N$4,2))) -> 0
A88: TXN-1498 | B88: 7 | C88: Jul | D88: Q3 | E88: Sales | F88: Commissions | G88: Distributor Bonus | H88: 34200 | I88: Deepa Patel | K88: =IF(J88=$N$2,0,IF(J88=$N$3,1,IF(J88=$N$4,2))) -> 0
A89: TXN-1740 | B89: 11 | C89: Nov | D89: Q4 | E89: Marketing | F89: Events | G89: Eventbrite Pro | H89: 54800 | I89: Rahul Mehta | K89: =IF(J89=$N$2,0,IF(J89=$N$3,1,IF(J89=$N$4,2))) -> 0
A90: TXN-1437 | B90: 7 | C90: Jul | D90: Q3 | E90: HR | F90: Training | G90: LinkedIn Learning | H90: 800 | I90: Priya Sharma | K90: =IF(J90=$N$2,0,IF(J90=$N$3,1,IF(J90=$N$4,2))) -> 0
A91: TXN-1189 | B91: 3 | C91: Mar | D91: Q1 | E91: Operations | F91: Logistics | G91: Delhivery | H91: 38100 | I91: Sunita Rao | K91: =IF(J91=$N$2,0,IF(J91=$N$3,1,IF(J91=$N$4,2))) -> 0
A92: TXN-1108 | B92: 2 | C92: Feb | D92: Q1 | E92: Operations | F92: Payroll | G92: Gusto HR | H92: 34000 | I92: Sunita Rao | K92: =IF(J92=$N$2,0,IF(J92=$N$3,1,IF(J92=$N$4,2))) -> 0
A93: TXN-1781 | B93: 11 | C93: Nov | D93: Q4 | E93: Finance | F93: Training | G93: LinkedIn Learning | H93: 6400 | I93: Vikram Joshi | K93: =IF(J93=$N$2,0,IF(J93=$N$3,1,IF(J93=$N$4,2))) -> 0
A94: TXN-1524 | B94: 8 | C94: Aug | D94: Q3 | E94: Marketing | F94: Ad Spend | G94: LinkedIn Ads | H94: 8500 | I94: Rahul Mehta | K94: =IF(J94=$N$2,0,IF(J94=$N$3,1,IF(J94=$N$4,2))) -> 0
A95: TXN-1796 | B95: 12 | C95: Dec | D95: Q4 | E95: HR | F95: Payroll | G95: Gusto HR | H95: 110100 | I95: Priya Sharma | K95: =IF(J95=$N$2,0,IF(J95=$N$3,1,IF(J95=$N$4,2))) -> 0
A96: TXN-1001 | B96: 1 | C96: Jan | D96: Q1 | E96: HR | F96: Payroll | G96: ADP Payroll Services | H96: 324500 | I96: Priya Sharma | K96: =IF(J96=$N$2,0,IF(J96=$N$3,1,IF(J96=$N$4,2))) -> 0
A97: TXN-1706 | B97: 10 | C97: Oct | D97: Q4 | E97: Finance | F97: Software Licenses | G97: Microsoft 365 | H97: 23600 | I97: Vikram Joshi | K97: =IF(J97=$N$2,0,IF(J97=$N$3,1,IF(J97=$N$4,2))) -> 0
... A106: TXN-1223 | B106: 4 | C106: Apr | D106: Q2 | E106: HR | F106: Payroll | G106: Paychex | H106: 104800 | I106: Priya Sharma | K106: =IF(J106=$N$2,0,IF(J106=$N$3,1,IF(J106=$N$4,2))) -> 0
A107: TXN-1203 | B107: 3 | C107: Mar | D107: Q1 | E107: Finance | F107: Audit Fees | G107: Deloitte India | H107: 7700 | I107: Vikram Joshi | J107: Budget overrun - approved by CFO | K107: =IF(J107=$N$2,0,IF(J107=$N$3,1,IF(J107=$N$4,2))) -> 1
A108: TXN-1174 | B108: 3 | C108: Mar | D108: Q1 | E108: IT | F108: Payroll | G108: Gusto HR | H108: 32400 | I108: Arjun Nair | K108: =IF(J108=$N$2,0,IF(J108=$N$3,1,IF(J108=$N$4,2))) -> 0
A109: TXN-1257 | B109: 4 | C109: Apr | D109: Q2 | E109: Operations | F109: Payroll | G109: Paychex | H109: 124600 | I109: Sunita Rao | K109: =IF(J109=$N$2,0,IF(J109=$N$3,1,IF(J109=$N$4,2))) -> 0
A110: TXN-1450 | B110: 7 | C110: Jul | D110: Q3 | E110: Marketing | F110: Events | G110: Town Hall Venue | H110: 45700 | I110: Rahul Mehta | K110: =IF(J110=$N$2,0,IF(J110=$N$3,1,IF(J110=$N$4,2))) -> 0
A111: TXN-1616 | B111: 9 | C111: Oct | D111: Q3 | E111: Operations | F111: Payroll | G111: Paychex | H111: 29200 | I111: Sunita Rao | K111: =IF(J111=$N$2,0,IF(J111=$N$3,1,IF(J111=$N$4,2))) -> 0
A112: TXN-1467 | B112: 7 | C112: Jul | D112: Q3 | E112: Operations | F112: Payroll | G112: Paychex | H112: 275000 | I112: Sunita Rao | K112: =IF(J112=$N$2,0,IF(J112=$N$3,1,IF(J112=$N$4,2))) -> 0
A113: TXN-1829 | B113: 12 | C113: Dec | D113: Q4 | E113: IT | F113: Software Licenses | G113: Microsoft 365 | H113: 1600 | I113: Arjun Nair | K113: =IF(J113=$N$2,0,IF(J113=$N$3,1,IF(J113=$N$4,2))) -> 0
A114: TXN-1643 | B114: 9 | C114: Oct | D114: Q3 | E114: Sales | F114: Commissions | G114: Distributor Bonus | H114: 99700 | I114: Deepa Patel | J114: Budget overrun - approved by CFO | K114: =IF(J114=$N$2,0,IF(J114=$N$3,1,IF(J114=$N$4,2))) -> 1
A115: TXN-1637 | B115: 9 | C115: Oct | D115: Q3 | E115: Finance | F115: Software Licenses | G115: Adobe Creative | H115: 5100 | I115: Vikram Joshi | K115: =IF(J115=$N$2,0,IF(J115=$N$3,1,IF(J115=$N$4,2))) -> 0
A116: TXN-1443 | B116: 7 | C116: Jul | D116: Q3 | E116: HR | F116: Travel | G116: SOTC Travel | H116: 3300 | I116: Priya Sharma | K116: =IF(J116=$N$2,0,IF(J116=$N$3,1,IF(J116=$N$4,2))) -> 0
A117: TXN-1843 | B117: 12 | C117: Dec | D117: Q4 | E117: Operations | F117: Travel | G117: SOTC Travel | H117: 5700 | I117: Sunita Rao | K117: =IF(J117=$N$2,0,IF(J117=$N$3,1,IF(J117=$N$4,2))) -> 0
A118: TXN-1512 | B118: 8 | C118: Aug | D118: Q3 | E118: HR | F118: Recruitment | G118: Naukri Corporate | H118: 17600 | I118: Priya Sharma | K118: =IF(J118=$N$2,0,IF(J118=$N$3,1,IF(J118=$N$4,2))) -> 0
A119: TXN-1853 | B119: 12 | C119: Dec | D119: Q4 | E119: Finance | F119: Audit Fees | G119: Deloitte India | H119: 44600 | I119: Vikram Joshi | J119: Budget overrun - approved by CFO | K119: =IF(J119=$N$2,0,IF(J119=$N$3,1,IF(J119=$N$4,2))) -> 1
A120: TXN-1559 | B120: 8 | C120: Aug | D120: Q3 | E120: Finance | F120: Audit Fees | G120: KPMG India | H120: 100 | I120: Vikram Joshi | K120: =IF(J120=$N$2,0,IF(J120=$N$3,1,IF(J120=$N$4,2))) -> 0
A121: TXN-1291 | B121: 4 | C121: Apr | D121: Q2 | E121: Sales | F121: Entertainment | G121: Client Dining | H121: 8400 | I121: Deepa Patel | K121: =IF(J121=$N$2,0,IF(J121=$N$3,1,IF(J121=$N$4,2))) -> 0
A122: TXN-1687 | B122: 10 | C122: Oct | D122: Q4 | E122: IT | F122: Hardware | G122: Dell Technologies | H122: 34500 | I122: Arjun Nair | J122: Budget overrun - approved by CFO | K122: =IF(J122=$N$2,0,IF(J122=$N$3,1,IF(J122=$N$4,2))) -> 1
A123: TXN-1754 | B123: 11 | C123: Nov | D123: Q4 | E123: IT | F123: Cloud Services | G123: Azure Enterprise | H123: 4900 | I123: Arjun Nair | K123: =IF(J123=$N$2,0,IF(J123=$N$3,1,IF(J123=$N$4,2))) -> 0
A124: TXN-1766 | B124: 11 | C124: Nov | D124: Q4 | E124: Operations | F124: Maintenance | G124: BuildCare | H124: 3100 | I124: Sunita Rao | K124: =IF(J124=$N$2,0,IF(J124=$N$3,1,IF(J124=$N$4,2))) -> 0
A125: TXN-1049 | B125: 1 | C125: Jan | D125: Q1 | E125: Finance | F125: Audit Fees | G125: PwC Advisory | H125: 15700 | I125: Vikram Joshi | K125: =IF(J125=$N$2,0,IF(J125=$N$3,1,IF(J125=$N$4,2))) -> 0
A126: TXN-1609 | B126: 9 | C126: Oct | D126: Q3 | E126: IT | F126: Hardware | G126: Lenovo B2B | H126: 24900 | I126: Arjun Nair | K126: =IF(J126=$N$2,0,IF(J126=$N$3,1,IF(J126=$N$4,2))) -> 0
A127: TXN-1793 | B127: 11 | C127: Nov | D127: Q4 | E127: Sales | F127: Entertainment | G127: Corporate Gifts | H127: 25900 | I127: Deepa Patel | K127: =IF(J127=$N$2,0,IF(J127=$N$3,1,IF(J127=$N$4,2))) -> 0
A128: TXN-1294 | B128: 5 | C128: May | D128: Q2 | E128: HR | F128: Payroll | G128: Paychex | H128: 162000 | I128: Priya Sharma | K128: =IF(J128=$N$2,0,IF(J128=$N$3,1,IF(J128=$N$4,2))) -> 0
A129: TXN-1172 | B129: 3 | C129: Mar | D129: Q1 | E129: IT | F129: Payroll | G129: Paychex | H129: 158900 | I129: Arjun Nair | K129: =IF(J129=$N$2,0,IF(J129=$N$3,1,IF(J129=$N$4,2))) -> 0
A130: TXN-1504 | B130: 8 | C130: Aug | D130: Q3 | E130: HR | F130: Payroll | G130: ADP Payroll Services | H130: 169100 | I130: Priya Sharma | K130: =IF(J130=$N$2,0,IF(J130=$N$3,1,IF(J130=$N$4,2))) -> 0
A131: TXN-1360 | B131: 5 | C131: May | D131: Q2 | E131: Sales | F131: Entertainment | G131: Client Dining | H131: 23900 | I131: Deepa Patel | K131: =IF(J131=$N$2,0,IF(J131=$N$3,1,IF(J131=$N$4,2))) -> 0
A132: TXN-1729 | B132: 11 | C132: Nov | D132: Q4 | E132: HR | F132: Travel | G132: MakeMyTrip Corporate | H132: 6500 | I132: Priya Sharma | K132: =IF(J132=$N$2,0,IF(J132=$N$3,1,IF(J132=$N$4,2))) -> 0
A133: TXN-1724 | B133: 11 | C133: Nov | D133: Q4 | E133: HR | F133: Payroll | G133: ADP Payroll Services | H133: 267300 | I133: Priya Sharma | K133: =IF(J133=$N$2,0,IF(J133=$N$3,1,IF(J133=$N$4,2))) -> 0
A134: TXN-1543 | B134: 8 | C134: Aug | D134: Q3 | E134: IT | F134: Cloud Services | G134: Google Cloud | H134: 101400 | I134: Arjun Nair | K134: =IF(J134=$N$2,0,IF(J134=$N$3,1,IF(J134=$N$4,2))) -> 0
... A144: TXN-1820 | B144: 12 | C144: Dec | D144: Q4 | E144: Marketing | F144: Travel | G144: SOTC Travel | H144: 2900 | I144: Rahul Mehta | K144: =IF(J144=$N$2,0,IF(J144=$N$3,1,IF(J144=$N$4,2))) -> 0
A145: TXN-1500 | B145: 7 | C145: Jul | D145: Q3 | E145: Sales | F145: Travel | G145: MakeMyTrip Corporate | H145: 44400 | I145: Deepa Patel | J145: Budget overrun - approved by CFO | K145: =IF(J145=$N$2,0,IF(J145=$N$3,1,IF(J145=$N$4,2))) -> 1
A146: TXN-1099 | B146: 2 | C146: Feb | D146: Q1 | E146: IT | F146: Software Licenses | G146: Atlassian Suite | H146: 52600 | I146: Arjun Nair | K146: =IF(J146=$N$2,0,IF(J146=$N$3,1,IF(J146=$N$4,2))) -> 0
A147: TXN-1376 | B147: 6 | C147: Jun | D147: Q2 | E147: Marketing | F147: Payroll | G147: Gusto HR | H147: 184800 | I147: Rahul Mehta | K147: =IF(J147=$N$2,0,IF(J147=$N$3,1,IF(J147=$N$4,2))) -> 0
A148: TXN-1139 | B148: 2 | C148: Feb | D148: Q1 | E148: Sales | F148: Travel | G148: SOTC Travel | H148: 5000 | I148: Deepa Patel | K148: =IF(J148=$N$2,0,IF(J148=$N$3,1,IF(J148=$N$4,2))) -> 0
A149: TXN-1811 | B149: 12 | C149: Dec | D149: Q4 | E149: Marketing | F149: Ad Spend | G149: Google Ads | H149: 39200 | I149: Rahul Mehta | K149: =IF(J149=$N$2,0,IF(J149=$N$3,1,IF(J149=$N$4,2))) -> 0
A150: TXN-1410 | B150: 6 | C150: Jun | D150: Q2 | E150: Finance | F150: Audit Fees | G150: KPMG India | H150: 7400 | I150: Vikram Joshi | K150: =IF(J150=$N$2,0,IF(J150=$N$3,1,IF(J150=$N$4,2))) -> 0
...

Sheet Budget_Table
A1: Lookup_Key | B1: Department | C1: Expense_Category | D1: Month_Num | E1: Month_Name | F1: Quarter | G1: Annual_Budget (INR) | H1: Monthly_Budget (INR) | I1: Actual_Budget
A2: HR|Payroll|1 | B2: HR | C2: Payroll | D2: 1 | E2: Jan | F2: Q1 | G2: 5141000 | H2: 378000 | I2: =H2*12 -> 4536000
A3: HR|Training|1 | B3: HR | C3: Training | D3: 1 | E3: Jan | F3: Q1 | G3: 428000 | H3: 32000 | I3: =H3*12 -> 384000
A4: HR|Recruitment|1 | B4: HR | C4: Recruitment | D4: 1 | E4: Jan | F4: Q1 | G4: 673000 | H4: 50000 | I4: =H4*12 -> 600000
A5: HR|Travel|1 | B5: HR | C5: Travel | D5: 1 | E5: Jan | F5: Q1 | G5: 220000 | H5: 16000 | I5: =H5*12 -> 192000
A6: Marketing|Payroll|1 | B6: Marketing | C6: Payroll | D6: 1 | E6: Jan | F6: Q1 | G6: 4651000 | H6: 342000 | I6: =H6*12 -> 4104000
A7: Marketing|Ad Spend|1 | B7: Marketing | C7: Ad Spend | D7: 1 | E7: Jan | F7: Q1 | G7: 1836000 | H7: 135000 | I7: =H7*12 -> 1620000
A8: Marketing|Events|1 | B8: Marketing | C8: Events | D8: 1 | E8: Jan | F8: Q1 | G8: 857000 | H8: 63000 | I8: =H8*12 -> 756000
A9: Marketing|Travel|1 | B9: Marketing | C9: Travel | D9: 1 | E9: Jan | F9: Q1 | G9: 306000 | H9: 22000 | I9: =H9*12 -> 264000
A10: IT|Payroll|1 | B10: IT | C10: Payroll | D10: 1 | E10: Jan | F10: Q1 | G10: 6120000 | H10: 450000 | I10: =H10*12 -> 5400000
A11: IT|Software Licenses|1 | B11: IT | C11: Software Licenses | D11: 1 | E11: Jan | F11: Q1 | G11: 1102000 | H11: 81000 | I11: =H11*12 -> 972000
A12: IT|Hardware|1 | B12: IT | C12: Hardware | D12: 1 | E12: Jan | F12: Q1 | G12: 979000 | H12: 72000 | I12: =H12*12 -> 864000
A13: IT|Cloud Services|1 | B13: IT | C13: Cloud Services | D13: 1 | E13: Jan | F13: Q1 | G13: 1346000 | H13: 99000 | I13: =H13*12 -> 1188000
... A289: Sales|Entertainment|12 | B289: Sales | C289: Entertainment | D289: 12 | E289: Dec | F289: Q4 | G289: 367000 | H289: 36000 | I289: =H289*12 -> 432000

Sheet Variance_Tracker
A1: BUDGET vs. ACTUAL — VARIANCE TRACKER | FY 2024
A2: Source: Raw_Actuals Sheet | Budget Reference: Budget_Table Sheet | Formulas: XLOOKUP · SUMIFS · Conditional Formatting
A4: Lookup_Key | B4: Department | C4: Expense_Category | D4: Month_Num | E4: Month_Name | F4: Quarter | G4: Monthly_Budget (INR) | H4: Actual (INR) | I4: Variance (INR) | J4: Variance % | K4: Status | L4: Notes
A5: HR|Payroll|1 | B5: HR | C5: Payroll | D5: 1 | E5: Jan | F5: Q1 | G5: 378000 | H5: =SUMIFS(Raw_Actuals!$H:$H,Raw_Actuals!$E:$E,B5,Raw_Actuals!$F:$F,C5,Raw_Actuals!$B:$B,D5) -> 437600 | I5: =H5-G5 -> 59600 | J5: =IFERROR(I5/G5,0) -> 0.15767196 | K5: =IF(J5>0.15,"🔴 Over Budget",IF(J5<-0.1,"🟡 Under Budget","🟢 On Track")) -> 🔴 Over Budget | L5: =IFERROR(IF(J5>0.15,"Overspend: review with dept head",IF(J5<-0.1,"Underspend: check if deferred","")),"") -> Overspend: review with dept head
A6: HR|Training|1 | B6: HR | C6: Training | D6: 1 | E6: Jan | F6: Q1 | G6: 32000 | H6: =SUMIFS(Raw_Actuals!$H:$H,Raw_Actuals!$E:$E,B6,Raw_Actuals!$F:$F,C6,Raw_Actuals!$B:$B,D6) -> 31200 | I6: =H6-G6 -> -800 | J6: =IFERROR(I6/G6,0) -> -0.025 | K6: =IF(J6>0.15,"🔴 Over Budget",IF(J6<-0.1,"🟡 Under Budget","🟢 On Track")) -> 🟢 On Track | L6: =IFERROR(IF(J6>0.15,"Overspend: review with dept head",IF(J6<-0.1,"Underspend: check if deferred","")),"")
A7: HR|Recruitment|1 | B7: HR | C7: Recruitment | D7: 1 | E7: Jan | F7: Q1 | G7: 50000 | H7: =SUMIFS(Raw_Actuals!$H:$H,Raw_Actuals!$E:$E,B7,Raw_Actuals!$F:$F,C7,Raw_Actuals!$B:$B,D7) -> 56500 | I7: =H7-G7 -> 6500 | J7: =IFERROR(I7/G7,0) -> 0.13 | K7: =IF(J7>0.15,"🔴 Over Budget",IF(J7<-0.1,"🟡 Under Budget","🟢 On Track")) -> 🟢 On Track | L7: =IFERROR(IF(J7>0.15,"Overspend: review with dept head",IF(J7<-0.1,"Underspend: check if deferred","")),"")
A8: HR|Travel|1 | B8: HR | C8: Travel | D8: 1 | E8: Jan | F8: Q1 | G8: 16000 | H8: =SUMIFS(Raw_Actuals!$H:$H,Raw_Actuals!$E:$E,B8,Raw_Actuals!$F:$F,C8,Raw_Actuals!$B:$B,D8) -> 18000 | I8: =H8-G8 -> 2000 | J8: =IFERROR(I8/G8,0) -> 0.125 | K8: =IF(J8>0.15,"🔴 Over Budget",IF(J8<-0.1,"🟡 Under Budget","🟢 On Track")) -> 🟢 On Track | L8: =IFERROR(IF(J8>0.15,"Overspend: review with dept head",IF(J8<-0.1,"Underspend: check if deferred","")),"")
A9: Marketing|Payroll|1 | B9: Marketing | C9: Payroll | D9: 1 | E9: Jan | F9: Q1 | G9: 342000 | H9: =SUMIFS(Raw_Actuals!$H:$H,Raw_Actuals!$E:$E,B9,Raw_Actuals!$F:$F,C9,Raw_Actuals!$B:$B,D9) -> 402900 | I9: =H9-G9 -> 60900 | J9: =IFERROR(I9/G9,0) -> 0.17807018 | K9: =IF(J9>0.15,"🔴 Over Budget",IF(J9<-0.1,"🟡 Under Budget","🟢 On Track")) -> 🔴 Over Budget | L9: =IFERROR(IF(J9>0.15,"Overspend: review with dept head",IF(J9<-0.1,"Underspend: check if deferred","")),"") -> Overspend: review with dept head
A10: Marketing|Ad Spend|1 | B10: Marketing | C10: Ad Spend | D10: 1 | E10: Jan | F10: Q1 | G10: 135000 | H10: =SUMIFS(Raw_Actuals!$H:$H,Raw_Actuals!$E:$E,B10,Raw_Actuals!$F:$F,C10,Raw_Actuals!$B:$B,D10) -> 146600 | I10: =H10-G10 -> 11600 | J10: =IFERROR(I10/G10,0) -> 0.085925926 | K10: =IF(J10>0.15,"🔴 Over Budget",IF(J10<-0.1,"🟡 Under Budget","🟢 On Track")) -> 🟢 On Track | L10: =IFERROR(IF(J10>0.15,"Overspend: review with dept head",IF(J10<-0.1,"Underspend: check if deferred","")),"")
A11: Marketing|Events|1 | B11: Marketing | C11: Events | D11: 1 | E11: Jan | F11: Q1 | G11: 63000 | H11: =SUMIFS(Raw_Actuals!$H:$H,Raw_Actuals!$E:$E,B11,Raw_Actuals!$F:$F,C11,Raw_Actuals!$B:$B,D11) -> 67400 | I11: =H11-G11 -> 4400 | J11: =IFERROR(I11/G11,0) -> 0.06984127 | K11: =IF(J11>0.15,"🔴 Over Budget",IF(J11<-0.1,"🟡 Under Budget","🟢 On Track")) -> 🟢 On Track | L11: =IFERROR(IF(J11>0.15,"Overspend: review with dept head",IF(J11<-0.1,"Underspend: check if deferred","")),"")
A12: Marketing|Travel|1 | B12: Marketing | C12: Travel | D12: 1 | E12: Jan | F12: Q1 | G12: 22000 | H12: =SUMIFS(Raw_Actuals!$H:$H,Raw_Actuals!$E:$E,B12,Raw_Actuals!$F:$F,C12,Raw_Actuals!$B:$B,D12) -> 25300 | I12: =H12-G12 -> 3300 | J12: =IFERROR(I12/G12,0) -> 0.15 | K12: =IF(J12>0.15,"🔴 Over Budget",IF(J12<-0.1,"🟡 Under Budget","🟢 On Track")) -> 🟢 On Track | L12: =IFERROR(IF(J12>0.15,"Overspend: review with dept head",IF(J12<-0.1,"Underspend: check if deferred","")),"")
A13: IT|Payroll|1 | B13: IT | C13: Payroll | D13: 1 | E13: Jan | F13: Q1 | G13: 450000 | H13: =SUMIFS(Raw_Actuals!$H:$H,Raw_Actuals!$E:$E,B13,Raw_Actuals!$F:$F,C13,Raw_Actuals!$B:$B,D13) -> 511600 | I13: =H13-G13 -> 61600 | J13: =IFERROR(I13/G13,0) -> 0.13688889 | K13: =IF(J13>0.15,"🔴 Over Budget",IF(J13<-0.1,"🟡 Under Budget","🟢 On Track")) -> 🟢 On Track | L13: =IFERROR(IF(J13>0.15,"Overspend: review with dept head",IF(J13<-0.1,"Underspend: check if deferred","")),"")
A14: IT|Software Licenses|1 | B14: IT | C14: Software Licenses | D14: 1 | E14: Jan | F14: Q1 | G14: 81000 | H14: =SUMIFS(Raw_Actuals!$H:$H,Raw_Actuals!$E:$E,B14,Raw_Actuals!$F:$F,C14,Raw_Actuals!$B:$B,D14) -> 84000 | I14: =H14-G14 -> 3000 | J14: =IFERROR(I14/G14,0) -> 0.037037037 | K14: =IF(J14>0.15,"🔴 Over Budget",IF(J14<-0.1,"🟡 Under Budget","🟢 On Track")) -> 🟢 On Track | L14: =IFERROR(IF(J14>0.15,"Overspend: review with dept head",IF(J14<-0.1,"Underspend: check if deferred","")),"")
A15: IT|Hardware|1 | B15: IT | C15: Hardware | D15: 1 | E15: Jan | F15: Q1 | G15: 72000 | H15: =SUMIFS(Raw_Actuals!$H:$H,Raw_Actuals!$E:$E,B15,Raw_Actuals!$F:$F,C15,Raw_Actuals!$B:$B,D15) -> 83600 | I15: =H15-G15 -> 11600 | J15: =IFERROR(I15/G15,0) -> 0.16111111 | K15: =IF(J15>0.15,"🔴 Over Budget",IF(J15<-0.1,"🟡 Under Budget","🟢 On Track")) -> 🔴 Over Budget | L15: =IFERROR(IF(J15>0.15,"Overspend: review with dept head",IF(J15<-0.1,"Underspend: check if deferred","")),"") -> Overspend: review with dept head
A16: IT|Cloud Services|1 | B16: IT | C16: Cloud Services | D16: 1 | E16: Jan | F16: Q1 | G16: 99000 | H16: =SUMIFS(Raw_Actuals!$H:$H,Raw_Actuals!$E:$E,B16,Raw_Actuals!$F:$F,C16,Raw_Actuals!$B:$B,D16) -> 116300 | I16: =H16-G16 -> 17300 | J16: =IFERROR(I16/G16,0) -> 0.17474747 | K16: =IF(J16>0.15,"🔴 Over Budget",IF(J16<-0.1,"🟡 Under Budget","🟢 On Track")) -> 🔴 Over Budget | L16: =IFERROR(IF(J16>0.15,"Overspend: review with dept head",IF(J16<-0.1,"Underspend: check if deferred","")),"") -> Overspend: review with dept head
... A292: Sales|Entertainment|12 | B292: Sales | C292: Entertainment | D292: 12 | E292: Dec | F292: Q4 | G292: 36000 | H292: =SUMIFS(Raw_Actuals!$H:$H,Raw_Actuals!$E:$E,B292,Raw_Actuals!$F:$F,C292,Raw_Actuals!$B:$B,D292) -> 26300 | I292: =H292-G292 -> -9700 | J292: =IFERROR(I292/G292,0) -> -0.26944444 | K292: =IF(J292>0.15,"🔴 Over Budget",IF(J292<-0.1,"🟡 Under Budget","🟢 On Track")) -> 🟡 Under Budget | L292: =IFERROR(IF(J292>0.15,"Overspend: review with dept head",IF(J292<-0.1,"Underspend: check if deferred","")),"") -> Underspend: check if deferred

Sheet Dashboard
A1: 📊 BUDGET vs. ACTUAL — EXECUTIVE DASHBOARD | FY 2024
A2: Source: Variance_Tracker | Drill into Department, Quarter, Status
P3: Department | Q3: Budget | R3: Actual | S3: Variance | U3: Department | V3: Variance
B4: TOTAL BUDGET | D4: TOTAL ACTUAL | F4: TOTAL VARIANCE | H4: VARIANCE % | P4: Finance | Q4: =SUMIFS(Variance_Tracker!G:G,Variance_Tracker!B:B,P4) -> 4650000 | R4: =SUMIFS(Variance_Tracker!H:H,Variance_Tracker!B:B,P4) -> 4562700 | S4: =R4-Q4 -> -87300 | U4: =P4 -> Finance | V4: =S4 -> -87300
B5: =SUM(Variance_Tracker!G5:G292) -> 43137000 | D5: =SUM(Variance_Tracker!H5:H292) -> 42004800 | F5: =D5-B5 -> -1132200 | H5: =IFERROR(F5/B5,0) -> -0.02624661 | P5: HR | Q5: =SUMIFS(Variance_Tracker!G:G,Variance_Tracker!B:B,P5) -> 6551000 | R5: =SUMIFS(Variance_Tracker!H:H,Variance_Tracker!B:B,P5) -> 6395000 | S5: =R5-Q5 -> -156000 | U5: =P5 -> HR | V5: =S5 -> -156000
P6: IT | Q6: =SUMIFS(Variance_Tracker!G:G,Variance_Tracker!B:B,P6) -> 9672000 | R6: =SUMIFS(Variance_Tracker!H:H,Variance_Tracker!B:B,P6) -> 9211900 | S6: =R6-Q6 -> -460100 | U6: =P6 -> IT | V6: =S6 -> -460100
B7: 📈 VARIANCE BY DEPARTMENT × QUARTER (INR) | U7: =P7 -> 0 | V7: =S7 -> 0
B8: Variance | C8: Column Labels | P8: Operations | Q8: =SUMIFS(Variance_Tracker!G:G,Variance_Tracker!B:B,P8) -> 5891000 | R8: =SUMIFS(Variance_Tracker!H:H,Variance_Tracker!B:B,P8) -> 5726100 | S8: =R8-Q8 -> -164900 | U8: =P8 -> Operations | V8: =S8 -> -164900
B9: Row Labels | C9: Q1 | D9: Q2 | E9: Q3 | F9: Q4 | G9: Grand Total | P9: Sales | Q9: =SUMIFS(Variance_Tracker!G:G,Variance_Tracker!B:B,P9) -> 8621000 | R9: =SUMIFS(Variance_Tracker!H:H,Variance_Tracker!B:B,P9) -> 8459300 | S9: =R9-Q9 -> -161700 | U9: =P9 -> Sales | V9: =S9 -> -161700
B10: Finance | C10: 114000 | D10: -50700 | E10: -67200 | F10: -83400 | G10: -87300
B11: HR | C11: 130600 | D11: -16800 | E11: -62300 | F11: -207500 | G11: -156000
B12: IT | C12: 8100 | D12: -96900 | E12: -146700 | F12: -224600 | G12: -460100
B13: Marketing | C13: 123500 | D13: 115500 | E13: -167800 | F13: -173400 | G13: -102200
B14: Operations | C14: 50800 | D14: -32700 | E14: -47600 | F14: -135400 | G14: -164900
B15: Sales | C15: 99700 | D15: -143800 | E15: 108900 | F15: -226500 | G15: -161700
B16: Grand Total | C16: 526700 | D16: -225400 | E16: -382700 | F16: -1050800 | G16: -1132200
B21: 📊 DEPARTMENT ANALYSIS

Sheet 📋 README
A1: 📋 PROJECT GUIDE — Budget vs. Actual Variance Tracker
A3: 🗂️ SHEET STRUCTURE
A4: Raw_Actuals | B4: 200+ rows of transaction-level spending data across 6 departments, 12 months. This is your 'messy' source data.
A5: Budget_Table | B5: Master budget lookup table. Contains one row per Dept + Category + Month. Used as the XLOOKUP source range.
A6: Variance_Tracker | B6: The main analysis sheet. Pulls budget via XLOOKUP, calculates actuals via SUMIFS, computes variance, and applies conditional formatting.
A8: 📐 FORMULAS USED
A9: XLOOKUP | B9: =IFERROR(xlookup(A5, Budget_Table!$A:$A, Budget_Table!$H:$H, "Not Found"), 0) → Looks up monthly budget using a Dept|Category|Month key
A10: SUMIFS | B10: =SUMIFS(Raw_Actuals!$H:$H, Raw_Actuals!$E:$E, B5, Raw_Actuals!$F:$F, C5, Raw_Actuals!$B:$B, D5) → Sums actual spend matching Dept + Category + Month
A11: Variance | B11: =actual - budget (negative = underspend, positive = overspend)
A12: Variance % | B12: =variance / budget (formatted as %)
A13: Status Logic
A15: 🎨 CONDITIONAL FORMATTING RULES
A16: 🔴 Red (Over Budget) | B16: Variance % > 15% → Red fill + bold text → Needs dept head review
A17: 🟢 Green (On Track) | B17: -10% to +15% → Green fill → Within acceptable variance band
A18: 🟡 Yellow (Under Budget) | B18: Variance % < -10% → Yellow fill → Check if spend was deferred
A19: Data Bars | B19: Applied to Actual (INR) column to visually compare spend magnitudes
A21: 📊 NEXT STEPS — BUILD YOUR DASHBOARD
A22: Step 1 | B22: Insert a Pivot Table from Variance_Tracker → Rows: Department, Columns: Quarter, Values: Variance (INR)
A23: Step 2 | B23: Add slicers for Department, Quarter, and Status
A24: Step 3 | B24: Insert a clustered bar chart: Budget vs Actual by Department
A25: Step 4 | B25: Insert a waterfall chart of Variance (INR) by Department
A26: Step 5 | B26: Add KPI summary cells: Total Budget, Total Actual, Total Variance, Variance %
A27: Step 6 | B27: Apply a clean dark theme to the dashboard sheet
A29: 💡 KEY INSIGHTS TO LOOK FOR
A30: Insight 1 | B30: Which department consistently overspends across all quarters?
A31: Insight 2 | B31: Which expense category has the highest single-month variance?
A32: Insight 3 | B32: Are there seasonal patterns in overspend (e.g., Q4 hardware spikes)?
A33: Insight 4 | B33: Which department has the best budget discipline (least variance)?
A34: Insight 5 | B34: Do certain vendors appear repeatedly in the high-overspend transactions?
